{
  "version": "5",
  "dialect": "pg",
  "entries": [
    {
      "idx": 0,
      "version": "5",
      "when": 1695552669551,
      "tag": "0000_lumpy_stryfe",
      "breakpoints": true
    },
    {
      "idx": 1,
      "version": "5",
      "when": 1695558181075,
      "tag": "0001_curved_black_queen",
      "breakpoints": true
    },
    {
      "idx": 2,
      "version": "5",
      "when": 1695558595376,
      "tag": "0002_mean_wither",
      "breakpoints": true
    },
    {
      "idx": 3,
      "version": "5",
      "when": 1695560738660,
      "tag": "0003_tan_franklin_storm",
      "breakpoints": true
    },
    {
      "idx": 4,
      "version": "5",
      "when": 1695647396893,
      "tag": "0004_real_songbird",
      "breakpoints": true
    },
    {
      "idx": 5,
      "version": "5",
      "when": 1695661830828,
      "tag": "0005_perfect_mongu",
      "breakpoints": true
    }
  ]
}